graiax_sayamod_requireez/__init__.py
graiax_sayamod_requireez-0.1.0.dist-info/WHEEL
graiax_sayamod_requireez-0.1.0.dist-info/METADATA
graiax_sayamod_requireez-0.1.0.dist-info/RECORD
